femwell/__init__.py
femwell/coulomb.py
femwell/culomb.py
femwell/eme.py.bak
femwell/examples/__init__.py
femwell/examples/coplanar_waveguide.py
femwell/fefd.py
femwell/fefd_2d.py
femwell/fiber.py
femwell/laplace.py
femwell/maxwell/__init__.py
femwell/maxwell/waveguide.py
femwell/mesh/__init__.py
femwell/mesh/mesh.py
femwell/mesh/meshtracker.py
femwell/mesh/slice.py
femwell/mesh.py
femwell/mode_solver_1d.py
femwell/mode_solver_2d_periodic.py
femwell/mode_solver_2d_periodic_quadratic.py
femwell/mode_solver_inplane.py
femwell/mode_solver_schrodinger.py
femwell/pn_analytical.py
femwell/solver.py
femwell/tcad.py
femwell/tests/test_mesh.py
femwell/thermal.py
femwell/thermal_transient.py
femwell/utils.py
femwell/visualization.py
femwell/waveguide.py
femwell-0.1.11.dist-info/LICENSE
femwell-0.1.11.dist-info/METADATA
femwell-0.1.11.dist-info/WHEEL
femwell-0.1.11.dist-info/RECORD
