Metadata-Version: 2.1
Name: femwell
Version: 0.1.11
Summary: Mode solver for photonic and electric waveguides based on FEM
Home-page: https://github.com/HelgeGehring/femwell
License: GPLv3
Keywords: integrated photonics,silicon photonics,mode solving,finite element analysis
Author: Helge Gehring
Requires-Python: >=3.8
Classifier: Development Status :: 4 - Beta
Classifier: Intended Audience :: Science/Research
Classifier: License :: Other/Proprietary License
Classifier: Programming Language :: Python :: 3
Classifier: Programming Language :: Python :: 3.8
Classifier: Programming Language :: Python :: 3.9
Classifier: Programming Language :: Python :: 3.10
Classifier: Programming Language :: Python :: 3.11
Classifier: Programming Language :: Python :: 3.12
Classifier: Topic :: Scientific/Engineering
Requires-Dist: gmsh
Requires-Dist: matplotlib
Requires-Dist: meshwell (>=1.0.2)
Requires-Dist: pygmsh
Requires-Dist: scikit-fem (>=8.1.0)
Project-URL: Documentation, https://HelgeGehring.github.io/femwell/
